README.rst
setup.py
livefyre/__init__.py
livefyre.egg-info/PKG-INFO
livefyre.egg-info/SOURCES.txt
livefyre.egg-info/dependency_links.txt
livefyre.egg-info/requires.txt
livefyre.egg-info/top_level.txt
livefyre.egg-info/zip-safe
livefyre/src/__init__.py
livefyre/src/api/__init__.py
livefyre/src/api/domain.py
livefyre/src/api/personalizedstream.py
livefyre/src/core/__init__.py
livefyre/src/core/collection/__init__.py
livefyre/src/core/collection/model.py
livefyre/src/core/collection/type.py
livefyre/src/core/collection/validator.py
livefyre/src/core/network/__init__.py
livefyre/src/core/network/model.py
livefyre/src/core/network/validator.py
livefyre/src/core/site/__init__.py
livefyre/src/core/site/model.py
livefyre/src/core/site/validator.py
livefyre/src/cursor/__init__.py
livefyre/src/cursor/factory.py
livefyre/src/cursor/model.py
livefyre/src/cursor/validator.py
livefyre/src/dto/__init__.py
livefyre/src/dto/subscription.py
livefyre/src/dto/topic.py
livefyre/src/exceptions/__init__.py
livefyre/src/utils/__init__.py
livefyre/src/utils/validator.py
livefyre/tests/__init__.py
livefyre/tests/api/__init__.py
livefyre/tests/api/domain_test.py
livefyre/tests/api/personalized_stream_test.py
livefyre/tests/core/__init__.py
livefyre/tests/core/collection_test.py
livefyre/tests/core/network_test.py
livefyre/tests/core/site_test.py
livefyre/tests/cursor/__init__.py
livefyre/tests/cursor/cursor_test.py
livefyre/tests/dto/__init__.py
livefyre/tests/dto/subscription_test.py
livefyre/tests/dto/topic_test.py
livefyre/tests/factory/__init__.py
livefyre/tests/factory/cursor_factory_test.py
livefyre/tests/utils/__init__.py
livefyre/tests/utils/utils_test.py